earthdaily/earthone/__init__.py
earthdaily/earthone/exceptions.py
earthdaily/earthone/auth/__init__.py
earthdaily/earthone/auth/auth.py
earthdaily/earthone/auth/tests/__init__.py
earthdaily/earthone/auth/tests/test_auth.py
earthdaily/earthone/catalog/__init__.py
earthdaily/earthone/compute/__init__.py
earthdaily/earthone/config/__init__.py
earthdaily/earthone/config/settings.toml
earthdaily/earthone/config/tests/__init__.py
earthdaily/earthone/config/tests/test_config.py
earthdaily/earthone/core/__init__.py
earthdaily/earthone/core/catalog/__init__.py
earthdaily/earthone/core/catalog/attributes.py
earthdaily/earthone/core/catalog/band.py
earthdaily/earthone/core/catalog/blob.py
earthdaily/earthone/core/catalog/blob_download.py
earthdaily/earthone/core/catalog/blob_upload.py
earthdaily/earthone/core/catalog/catalog_base.py
earthdaily/earthone/core/catalog/catalog_client.py
earthdaily/earthone/core/catalog/event_api_destination.py
earthdaily/earthone/core/catalog/event_rule.py
earthdaily/earthone/core/catalog/event_schedule.py
earthdaily/earthone/core/catalog/event_subscription.py
earthdaily/earthone/core/catalog/helpers.py
earthdaily/earthone/core/catalog/image.py
earthdaily/earthone/core/catalog/image_collection.py
earthdaily/earthone/core/catalog/image_types.py
earthdaily/earthone/core/catalog/image_upload.py
earthdaily/earthone/core/catalog/named_catalog_base.py
earthdaily/earthone/core/catalog/product.py
earthdaily/earthone/core/catalog/scaling.py
earthdaily/earthone/core/catalog/search.py
earthdaily/earthone/core/catalog/task.py
earthdaily/earthone/core/catalog/cli/__init__.py
earthdaily/earthone/core/catalog/cli/bands.py
earthdaily/earthone/core/catalog/cli/blobs.py
earthdaily/earthone/core/catalog/cli/cli.py
earthdaily/earthone/core/catalog/cli/products.py
earthdaily/earthone/core/catalog/cli/utils.py
earthdaily/earthone/core/catalog/cli/tests/__init__.py
earthdaily/earthone/core/catalog/cli/tests/test_cli.py
earthdaily/earthone/core/catalog/tests/__init__.py
earthdaily_earthone-5.0.3.dist-info/licenses/LICENSE
earthdaily_earthone-5.0.3.dist-info/METADATA
earthdaily_earthone-5.0.3.dist-info/WHEEL
earthdaily_earthone-5.0.3.dist-info/entry_points.txt
earthdaily_earthone-5.0.3.dist-info/top_level.txt
earthdaily_earthone-5.0.3.dist-info/RECORD
